{
  "db_name": "SQLite",
  "query": "\n            SELECT `entries`.* \n            FROM `entries`\n            WHERE `entries`.`path` = ?",
  "describe": {
    "columns": [
      {
        "name": "id",
        "ordinal": 0,
        "type_info": "Integer"
      },
      {
        "name": "folder_id",
        "ordinal": 1,
        "type_info": "Integer"
      },
      {
        "name": "path",
        "ordinal": 2,
        "type_info": "Text"
      },
      {
        "name": "filename",
        "ordinal": 3,
        "type_info": "Text"
      },
      {
        "name": "suffix",
        "ordinal": 4,
        "type_info": "Text"
      },
      {
        "name": "date_created",
        "ordinal": 5,
        "type_info": "Datetime"
      },
      {
        "name": "date_modified",
        "ordinal": 6,
        "type_info": "Datetime"
      },
      {
        "name": "date_added",
        "ordinal": 7,
        "type_info": "Datetime"
      }
    ],
    "parameters": {
      "Right": 1
    },
    "nullable": [
      false,
      false,
      false,
      false,
      false,
      true,
      true,
      true
    ]
  },
  "hash": "5731b78e1d74bbde3e7afd006a8aafde8754b005a05a3c175eb6edb747264b6d"
}
